RefactoringguruShejimoshiFix1/README.md
RefactoringguruShejimoshiFix1/__init__.py
RefactoringguruShejimoshiFix1/__main__.py
RefactoringguruShejimoshiFix1/file.epub
RefactoringguruShejimoshiFix1/index.html
RefactoringguruShejimoshiFix1/css/__init__.py
RefactoringguruShejimoshiFix1/css/annotations.css
RefactoringguruShejimoshiFix1/css/main.css
RefactoringguruShejimoshiFix1/css/normalize.css
RefactoringguruShejimoshiFix1/css/popup.css
RefactoringguruShejimoshiFix1/font/__init__.py
RefactoringguruShejimoshiFix1/font/fontello.eot
RefactoringguruShejimoshiFix1/font/fontello.svg
RefactoringguruShejimoshiFix1/font/fontello.ttf
RefactoringguruShejimoshiFix1/font/fontello.woff
RefactoringguruShejimoshiFix1/img/__init__.py
RefactoringguruShejimoshiFix1/img/annotator-glyph-sprite.png
RefactoringguruShejimoshiFix1/img/annotator-icon-sprite.png
RefactoringguruShejimoshiFix1/img/apple-touch-icon.png
RefactoringguruShejimoshiFix1/img/cancelfullscreen.png
RefactoringguruShejimoshiFix1/img/close.png
RefactoringguruShejimoshiFix1/img/fullscreen.png
RefactoringguruShejimoshiFix1/img/loader.gif
RefactoringguruShejimoshiFix1/img/menu-icon.png
RefactoringguruShejimoshiFix1/img/save.png
RefactoringguruShejimoshiFix1/img/saved.png
RefactoringguruShejimoshiFix1/img/settings-s.png
RefactoringguruShejimoshiFix1/img/settings.png
RefactoringguruShejimoshiFix1/img/star.png
RefactoringguruShejimoshiFix1/js/__init__.py
RefactoringguruShejimoshiFix1/js/epub.js
RefactoringguruShejimoshiFix1/js/epub.min.js
RefactoringguruShejimoshiFix1/js/epub.min.map
RefactoringguruShejimoshiFix1/js/hooks.min.js
RefactoringguruShejimoshiFix1/js/hooks.min.map
RefactoringguruShejimoshiFix1/js/reader.js
RefactoringguruShejimoshiFix1/js/reader.js.map
RefactoringguruShejimoshiFix1/js/reader.min.js
RefactoringguruShejimoshiFix1/js/reader.min.map
RefactoringguruShejimoshiFix1/js/hooks/__init__.py
RefactoringguruShejimoshiFix1/js/hooks/extensions/__init__.py
RefactoringguruShejimoshiFix1/js/hooks/extensions/highlight.js
refactoringguru_shejimoshi_fix1-2025.3.24.1.dist-info/METADATA
refactoringguru_shejimoshi_fix1-2025.3.24.1.dist-info/WHEEL
refactoringguru_shejimoshi_fix1-2025.3.24.1.dist-info/entry_points.txt
refactoringguru_shejimoshi_fix1-2025.3.24.1.dist-info/top_level.txt
refactoringguru_shejimoshi_fix1-2025.3.24.1.dist-info/RECORD
